setup.py
threaded_serial/__init__.py
threaded_serial/threaded_serial.py
threaded_serial.egg-info/PKG-INFO
threaded_serial.egg-info/SOURCES.txt
threaded_serial.egg-info/dependency_links.txt
threaded_serial.egg-info/not-zip-safe
threaded_serial.egg-info/requires.txt
threaded_serial.egg-info/top_level.txt