Metadata-Version: 1.0
Name: threaded-serial
Version: 0.1
Summary: Threaded Serial Manager
Home-page: https://github.com/zidik/threaded_serial
Author: Mark Laane
Author-email: marklaane+threaded_serial@gmail.com
License: MIT
Platform: UNKNOWN
